[
    { "name": "Super Força", "description": "Possui uma força sobre-humana.", "color": "#FF0000" },
    { "name": "Voo", "description": "Capacidade de voar.", "color": "#00FFFF" },
    { "name": "Regeneração", "description": "Pode se curar rapidamente de ferimentos.", "color": "#00FF00" },
    { "name": "Telepatia", "description": "Pode ler e controlar mentes.", "color": "#800080" },
    { "name": "Invisibilidade", "description": "Capacidade de se tornar invisível.", "color": "#FFFF00" },
    { "name": "Super Velocidade", "description": "Pode se mover em velocidades extremas.", "color": "#FFA500" },
    { "name": "Telecinese", "description": "Manipulação de objetos com a mente.", "color": "#8A2BE2" },
    { "name": "Elasticidade", "description": "Corpo flexível e elástico.", "color": "#FF00FF" },
    { "name": "Pirocinese", "description": "Capacidade de criar e controlar o fogo.", "color": "#FF4500" },
    { "name": "Mimetismo Animal", "description": "Habilidade de assumir características de animais.", "color": "#008000" },
    { "name": "Teletransporte", "description": "Pode se deslocar instantaneamente para diferentes lugares.", "color": "#0000FF" },
    { "name": "Invulnerabilidade", "description": "Imune a danos e ferimentos.", "color": "#FF1493" },
    { "name": "Magnetismo", "description": "Controle sobre campos magnéticos.", "color": "#FFC0CB" },
    { "name": "Precisão", "description": "Habilidade de nunca errar um alvo.", "color": "#FFD700" },
    { "name": "Hipnose", "description": "Pode controlar a mente dos outros.", "color": "#9400D3" },
    { "name": "Manipulação de Plantas", "description": "Controle sobre plantas e vegetação.", "color": "#008080" },
    { "name": "Incorporalidade", "description": "Capacidade de se tornar incorpóreo.", "color": "#C0C0C0" },
    { "name": "Criocinese", "description": "Capacidade de criar e controlar gelo.", "color": "#87CEEB" },
    { "name": "Camuflagem", "description": "Habilidade de se camuflar e se tornar invisível.", "color": "#556B2F" },
    { "name": "Geração de Escudos", "description": "Pode criar escudos protetores.", "color": "#4B0082" },
    { "name": "Super Sentidos", "description": "Sentidos aguçados além dos humanos.", "color": "#800000" },
    { "name": "Levitação", "description": "Capacidade de flutuar e levitar.", "color": "#FF69B4" },
    { "name": "Controle do Clima", "description": "Pode manipular o clima e as condições atmosféricas.", "color": "#4169E1" },
    { "name": "Intangibilidade", "description": "Pode atravessar objetos sólidos.", "color": "#6A5ACD" },
    { "name": "Super Inteligência", "description": "QI extraordinariamente alto.", "color": "#FF8C00" },
    { "name": "Eletrocinese", "description": "Capacidade de gerar e controlar eletricidade.", "color": "#FF6347" },
    { "name": "Manipulação de Som", "description": "Controle sobre ondas sonoras.", "color": "#9932CC" },
    { "name": "Visão de Raios-X", "description": "Capacidade de enxergar através de objetos.", "color": "#20B2AA" },
    { "name": "Hidrocinese", "description": "Capacidade de manipular e controlar água.", "color": "#00CED1" },
    { "name": "Armadura Sobre-Humana", "description": "Pele resistente como uma armadura.", "color": "#DC143C" },
    { "name": "Camuflagem Adaptação", "description": "Pode se adaptar ao ambiente para se tornar invisível.", "color": "#2E8B57" },
    { "name": "Mimetismo Elemental", "description": "Pode assumir as propriedades de elementos naturais.", "color": "#9932CC" },
    { "name": "Leitura de Mentes", "description": "Capacidade de ler os pensamentos das pessoas.", "color": "#FF1493" },
    { "name": "Cura", "description": "Capacidade de curar ferimentos e doenças.", "color": "#32CD32" },
    { "name": "Manipulação Gravitacional", "description": "Controle sobre a gravidade.", "color": "#800080" },
    { "name": "Super Agilidade", "description": "Reflexos rápidos e movimentos ágeis.", "color": "#FFD700" },
    { "name": "Escudo Energético", "description": "Capacidade de criar escudos de energia.", "color": "#00FF7F" },
    { "name": "Criação de Portais", "description": "Pode criar portais para se deslocar entre locais.", "color": "#FF00FF" },
    { "name": "Visão Noturna", "description": "Capacidade de enxergar no escuro.", "color": "#000080" },
    { "name": "Amplificação de Poder", "description": "Capacidade de aumentar os poderes próprios ou de outros.", "color": "#FFA500" },
    { "name": "Manipulação Temporal", "description": "Controle sobre o tempo.", "color": "#8B0000" },
    { "name": "Criação de Ilusões", "description": "Pode criar ilusões que enganam os sentidos.", "color": "#FF4500" },
    { "name": "Adaptação Ambiental", "description": "Capacidade de se adaptar a diferentes ambientes.", "color": "#808000" },
    { "name": "Reflexão de Projéteis", "description": "Capacidade de refletir projéteis.", "color": "#FFA07A" },
    { "name": "Transmutação", "description": "Capacidade de transformar a matéria.", "color": "#D2691E" },
    { "name": "Rajadas Ópticas", "description": "Pode disparar rajadas de energia pelos olhos.", "color":"#FF4500" },
    { "name": "Manipulação da Realidade", "description": "Capacidade de alterar a realidade conforme desejado.", "color": "#8B4513" },
    { "name": "Sopro de Gelo", "description": "Capacidade de expelir rajadas de gelo pela boca.", "color": "#00BFFF" },
    { "name": "Geração de Campos de Força", "description": "Pode criar campos de força protetores.", "color": "#FF8C00" },
    { "name": "Invisibilidade Psíquica", "description": "Capacidade de se tornar invisível para poderes psíquicos.", "color": "#4B0082" },
    { "name": "Controle de Energia", "description": "Capacidade de manipular e controlar diferentes formas de energia.", "color": "#FF00FF" },
    { "name": "Adesão à Parede", "description": "Capacidade de aderir e escalar superfícies verticais.", "color": "#800000" },
    { "name": "Geração de Explosões", "description": "Pode gerar explosões de energia.", "color": "#FFD700" },
    { "name": "Curvatura do Espaço", "description": "Pode curvar o espaço para viajar ou teletransportar.", "color": "#4B0082" },
    { "name": "Transformação Animal", "description": "Capacidade de se transformar em diferentes animais.", "color": "#008080" },
    { "name": "Manipulação da Gravidade", "description": "Capacidade de manipular a gravidade ao redor.", "color": "#9932CC" },
    { "name": "Invisibilidade Térmica", "description": "Capacidade de se tornar invisível para detectores de calor.", "color": "#FF1493" },
    { "name": "Absorção de Energia", "description": "Capacidade de absorver e usar diferentes formas de energia.", "color": "#FF8C00" },
    { "name": "Retrocognição", "description": "Capacidade de ver eventos passados.", "color": "#008000" },
    { "name": "Translocação", "description": "Capacidade de se teletransportar dentro de uma área limitada.", "color": "#00CED1" },
    { "name": "Sensibilidade Animal", "description": "Capacidade de se comunicar e entender animais.", "color": "#FF4500" },
    { "name": "Mimetismo de Energia", "description": "Pode assumir a forma e os poderes de diferentes tipos de energia.", "color": "#9932CC" },
    { "name": "Manipulação de Sonhos", "description": "Capacidade de controlar e manipular sonhos.", "color": "#8A2BE2" },
    { "name": "Criação de Barreiras", "description": "Pode criar barreiras protetoras.", "color": "#FFD700" },
    { "name": "Imitação Vocal", "description": "Pode imitar perfeitamente qualquer voz.", "color": "#808080" },
    { "name": "Aceleração Molecular", "description": "Capacidade de acelerar ou desacelerar as moléculas.", "color": "#87CEEB" },
    { "name": "Cura Acelerada", "description": "Capacidade de se curar rapidamente.", "color": "#32CD32" },
    { "name": "Telecinese Avançada", "description": "Capacidade de mover objetos com a mente em grandes proporções.", "color": "#FF0000" },
    { "name": "Criação de Campo de Força", "description": "Pode criar um escudo de proteção ao redor de si mesmo ou de outros.", "color": "#00FFFF" },
    { "name": "Manipulação da Energia Cinética", "description": "Capacidade de controlar e manipular a energia cinética.", "color": "#00FF00" },
    { "name": "Controle de Insetos", "description": "Pode se comunicar e controlar ações de insetos.", "color": "#800080" },
    { "name": "Sugestão Mental", "description": "Capacidade de influenciar os pensamentos e ações de outras pessoas.", "color": "#FFFF00" },
    { "name": "Super Salto", "description": "Pode saltar a alturas e distâncias extraordinárias.", "color": "#FFA500" },
    { "name": "Criopatia", "description": "Capacidade de diminuir a temperatura e congelar objetos.", "color": "#8A2BE2" },
    { "name": "Telecinese Molecular", "description": "Capacidade de manipular as moléculas dos objetos.", "color": "#FF00FF" },
    { "name": "Transformação da Pele", "description": "Pode alterar a aparência e textura da pele.", "color": "#FF4500" },
    { "name": "Invisibilidade Parcial", "description": "Capacidade de se tornar parcialmente invisível.", "color": "#008000" },
    { "name": "Absorção de Conhecimento", "description": "Capacidade de absorver conhecimento e informações instantaneamente.", "color": "#0000FF" },
    { "name": "Imitação de Voz", "description": "Pode imitar a voz de outras pessoas.", "color": "#FF1493" },
    { "name": "Mimetismo Elemental Avançado", "description": "Pode assumir as propriedades de elementos naturais em maior escala.", "color": "#FFC0CB" },
    { "name": "Precognição", "description": "Capacidade de ver eventos futuros.", "color": "#FFD700" },
    { "name": "Ecoquinese", "description": "Controle sobre ondas sonoras e seus efeitos.", "color": "#9400D3" },
    { "name": "Visão Térmica", "description": "Capacidade de enxergar o calor e identificar diferentes temperaturas.", "color": "#008080" },
    { "name": "Geração de Ilusões", "description": "Capacidade de criar ilusões visuais e auditivas.", "color": "#C0C0C0" },
    { "name": "Manipulação da Eletricidade", "description": "Controle sobre correntes elétricas e descargas.", "color": "#87CEEB" },
    { "name": "Explosões Psíquicas", "description": "Capacidade de gerar explosões psíquicas.", "color": "#9400D3" },
    { "name": "Controle de Ácido", "description": "Capacidade de manipular e controlar ácido.", "color": "#FF4500" },
    { "name": "Manipulação de Energia Vital", "description": "Controle sobre a energia vital de outros seres.", "color": "#9932CC" },
    { "name": "Mimetismo de Elementos", "description": "Capacidade de assumir as propriedades de elementos químicos.", "color": "#8A2BE2" },
    { "name": "Criação de Exércitos", "description": "Pode criar exércitos de seres ou criaturas.", "color": "#FFD700" },
    { "name": "Invisibilidade Molecular", "description": "Capacidade de tornar as moléculas do corpo invisíveis.", "color": "#4B0082" },
    { "name": "Controle de Radiação", "description": "Manipulação e emissão de radiação em várias formas.", "color": "#FF00FF" },
    { "name": "Manipulação de Energia Cinética", "description": "Capacidade de controlar e manipular a energia cinética.", "color": "#800000" },
    { "name": "Anulação de Magia", "description": "Poder para anular e neutralizar magias.", "color": "#FF6347" },
    { "name": "Manipulação de Antimatéria", "description": "Controle sobre a antimatéria e suas propriedades.", "color": "#9932CC" },
    { "name": "Imunidade Psíquica", "description": "Imune a ataques psíquicos e influência mental.", "color": "#8B0000" },
    { "name": "Criação de Construtos", "description": "Pode criar seres ou objetos feitos de energia.", "color": "#FF4500" },
    { "name": "Controle de Vírus", "description": "Capacidade de manipular e controlar vírus.", "color": "#808000" },
    { "name": "Intuição Sobrenatural", "description": "Capacidade de ter insights e conhecimento intuitivo.", "color": "#87CEEB" },
    { "name": "Manipulação de Densidade", "description": "Capacidade de controlar a densidade do próprio corpo.", "color": "#32CD32" },
    { "name": "Criação de Campos de Força", "description": "Pode criar campos de força para proteção.", "color": "#4B0082" },
    { "name": "Fusão Molecular", "description": "Capacidade de fundir moléculas e materiais.", "color": "#008080" },
    { "name": "Manipulação de Energia Solar", "description": "Controle sobre a energia solar e seus efeitos.", "color": "#9932CC" },
    { "name": "Teletransporte Local", "description": "Capacidade de se teletransportar para locais próximos.", "color": "#FFD700" },
    { "name": "Controle de Plantas", "description": "Capacidade de controlar o crescimento e comportamento das plantas.", "color": "#8A2BE2" },
    { "name": "Invisibilidade Temporal", "description": "Capacidade de se tornar temporariamente invisível.", "color": "#FFA500" },
    { "name": "Absorção de Energia", "description": "Capacidade de absorver e armazenar energia de várias fontes.", "color": "#4B0082" },
    { "name": "Manipulação de Som", "description": "Controle sobre o som e suas propriedades.", "color": "#FF00FF" },
    { "name": "Controle de Gravidade", "description": "Capacidade de manipular e controlar a força gravitacional.", "color": "#800000" },
    { "name": "Manipulação de Energia Elétrica", "description": "Controle sobre a eletricidade e descargas elétricas.", "color": "#8B0000" },
    { "name": "Projeção Astral", "description": "Capacidade de projetar a consciência para fora do corpo.", "color": "#FF4500" },
    { "name": "Controle de Temperatura", "description": "Capacidade de alterar a temperatura ambiente.", "color": "#808000" },
    { "name": "Leitura da Mente", "description": "Capacidade de ler os pensamentos de outras pessoas.", "color": "#87CEEB" },
    { "name": "Telecinese", "description": "Poder de mover objetos com a mente.", "color": "#32CD32" },
    { "name": "Controle de Fogo", "description": "Capacidade de criar e controlar o fogo.", "color": "#FF6347" },
    { "name": "Superforça", "description": "Capacidade de ter uma força sobre-humana.", "color": "#9932CC" },
    { "name": "Manipulação de Ilusões", "description": "Capacidade de criar ilusões sensoriais.", "color": "#8B0000" },
    { "name": "Controle de Gelo", "description": "Capacidade de criar e controlar gelo.", "color": "#808000" },
    { "name": "Invisibilidade", "description": "Capacidade de se tornar invisível aos olhos dos outros.", "color": "#FFA500" },
    { "name": "Manipulação de Energia Mental", "description": "Controle sobre a energia mental e psíquica.", "color": "#4B0082" },
    { "name": "Onipotência", "description": "Poder supremo e ilimitado.", "color": "#FFFFFF" },
    { "name": "Manipulação da Realidade Absoluta", "description": "Controle absoluto sobre a realidade.", "color": "#FFFFFF" },
    { "name": "Onisciência", "description": "Conhecimento absoluto e total.", "color": "#FFFFFF" },
    { "name": "Imortalidade", "description": "Incapaz de morrer ou envelhecer.", "color": "#FFFFFF" },
    { "name": "Destruição Universal", "description": "Poder para destruir todo o universo.", "color": "#FFFFFF" },
    { "name": "Criação de Mundos", "description": "Capacidade de criar novos universos e realidades.", "color": "#FFFFFF" },
    { "name": "Controle Temporal Absoluto", "description": "Poder para controlar o tempo em todos os aspectos.", "color": "#FFFFFF" },
    { "name": "Aniquilação Cósmica", "description": "Capacidade de aniquilar galáxias e sistemas estelares.", "color": "#FFFFFF" },
    { "name": "Influência Dimensional", "description": "Controle sobre diferentes dimensões e planos de existência.", "color": "#FFFFFF" },
    { "name": "Maior Manipulação de Energia", "description": "Capacidade de manipular todas as formas de energia.", "color": "#FFFFFF" },
    { "name": "Ressurreição Universal", "description": "Poder para ressuscitar todos os seres em um universo.", "color": "#FFFFFF" },
    { "name": "Conquista Multiversal", "description": "Capacidade de conquistar e governar múltiplos universos.", "color": "#FFFFFF" },
    { "name": "Onipresença", "description": "Capacidade de estar presente em todos os lugares ao mesmo tempo.", "color": "#FFFFFF" },
    { "name": "Eternidade", "description": "Existência eterna e imutável.", "color": "#FFFFFF" },
    { "name": "Invulnerabilidade Absoluta", "description": "Incapaz de ser ferido ou danificado de qualquer forma.", "color": "#FFFFFF" },
    { "name": "Controle sobre a Vida e a Morte", "description": "Poder para controlar a vida e a morte de todos os seres.", "color": "#FFFFFF" },
    { "name": "Manipulação de Almas Infinitas", "description": "Capacidade de controlar e manipular todas as almas.", "color": "#FFFFFF" },
    { "name": "Anulação de Poderes", "description": "Poder para anular os poderes de qualquer ser.", "color": "#FFFFFF" },
    { "name": "Conhecimento Absoluto", "description": "Conhecimento completo sobre todas as coisas.", "color": "#FFFFFF" },
    { "name": "Existência Primordial", "description": "Origem e essência fundamental do universo.", "color": "#FFFFFF" }
]